aliAgent/__init__.py
aliAgent/main.py
aliAgent/parse.py
aliAgent/database/ethic_ETHICS/test/gpt-3.5-turbo-1106_.log
aliAgent/database/ethic_ETHICS/test/llama2-13b_.log
aliAgent/database/examiner/chroma.sqlite3
aliAgent/database/law_traffic/base_test/generated_scenario/question_chatglm3-6b.csv
aliAgent/database/law_traffic/base_test/generated_scenario/question_gemini-pro.csv
aliAgent/database/law_traffic/base_test/generated_scenario/question_gpt-3.5-turbo-1106.csv
aliAgent/database/law_traffic/base_test/generated_scenario/question_gpt-4-1106-preview.csv
aliAgent/database/law_traffic/base_test/generated_scenario/question_llama2-13b.csv
aliAgent/database/law_traffic/base_test/generated_scenario/question_llama2-70b.csv
aliAgent/database/law_traffic/base_test/generated_scenario/question_llama2-7b.csv
aliAgent/database/law_traffic/base_test/generated_scenario/question_vicuna-13b.csv
aliAgent/database/law_traffic/base_test/generated_scenario/question_vicuna-33b.csv
aliAgent/database/law_traffic/base_test/generated_scenario/question_vicuna-7b.csv
aliAgent/dataset/gptfuzz_jb_prompts.csv
aliAgent/dataset/jailbreak.json
aliAgent/dataset/testing/ethic_ETHICS.json
aliAgent/dataset/testing/ethic_socialchemistry.json
aliAgent/dataset/testing/law_harmfulbehavior.json
aliAgent/dataset/testing/law_traffic.json
aliAgent/dataset/testing/stereotype_crows.json
aliAgent/dataset/testing/stereotype_decodingtrust.json
aliAgent/dataset/training/ethic_ETHICS.json
aliAgent/dataset/training/ethic_socialchemistry.json
aliAgent/dataset/training/law_harmfulbehavior.json
aliAgent/dataset/training/law_traffic.json
aliAgent/dataset/training/stereotype_crows.json
aliAgent/dataset/training/stereotype_decodingtrust.json
aliAgent/simulation/__init__.py
aliAgent/simulation/arena.py
aliAgent/simulation/examiner.py
aliAgent/simulation/utils.py
aliAgent/simulation/base/__init__.py
aliAgent/simulation/base/abstract_arena.py
aliAgent/simulation/base/abstract_examiner.py
ALI_Agent-0.2.4.dist-info/LICENSE
ALI_Agent-0.2.4.dist-info/METADATA
ALI_Agent-0.2.4.dist-info/WHEEL
ALI_Agent-0.2.4.dist-info/entry_points.txt
ALI_Agent-0.2.4.dist-info/top_level.txt
ALI_Agent-0.2.4.dist-info/RECORD
