Metadata-Version: 2.1
Name: ALI-Agent
Version: 0.2.4
Summary: A brief description of your project
Home-page: https://github.com/SophieZheng998/ALI-Agent
Author: Your Name
Author-email: your.email@example.com
Classifier: Programming Language :: Python :: 3
Classifier: License :: OSI Approved :: MIT License
Classifier: Operating System :: OS Independent
Requires-Python: >=3.9
License-File: LICENSE
Requires-Dist: ALI-Agent
Requires-Dist: Babel
Requires-Dist: Deprecated
Requires-Dist: GitPython
Requires-Dist: MarkupSafe
Requires-Dist: Pillow
Requires-Dist: PyPika
Requires-Dist: PyWavelets
Requires-Dist: PyYAML
Requires-Dist: QtPy
Requires-Dist: SecretStorage
Requires-Dist: Send2Trash
Requires-Dist: accelerate
Requires-Dist: aiofiles
Requires-Dist: aiohttp
Requires-Dist: aiosignal
Requires-Dist: annotated-types
Requires-Dist: anyio
Requires-Dist: appdirs
Requires-Dist: argon2-cffi
Requires-Dist: argon2-cffi-bindings
Requires-Dist: arrow
Requires-Dist: asgiref
Requires-Dist: asttokens
Requires-Dist: async-lru
Requires-Dist: async-timeout
Requires-Dist: attrs
Requires-Dist: azure-cognitiveservices-vision-computervision
Requires-Dist: azure-common
Requires-Dist: azure-core
Requires-Dist: azure-search-documents
Requires-Dist: backoff
Requires-Dist: backports.tarfile
Requires-Dist: bcrypt
Requires-Dist: beautifulsoup4
Requires-Dist: bleach
Requires-Dist: blessed
Requires-Dist: brotlipy
Requires-Dist: cachetools
Requires-Dist: certifi
Requires-Dist: cffi
Requires-Dist: charset-normalizer
Requires-Dist: chroma-hnswlib
Requires-Dist: chromadb
Requires-Dist: click
Requires-Dist: cmake
Requires-Dist: coloredlogs
Requires-Dist: comm
Requires-Dist: contourpy
Requires-Dist: cryptography
Requires-Dist: cycler
Requires-Dist: datasets
Requires-Dist: debugpy
Requires-Dist: decorator
Requires-Dist: deeprobust
Requires-Dist: defusedxml
Requires-Dist: dill
Requires-Dist: distro
Requires-Dist: docker-pycreds
Requires-Dist: docstring-parser
Requires-Dist: docutils
Requires-Dist: dpcpp-cpp-rt
Requires-Dist: exceptiongroup
Requires-Dist: executing
Requires-Dist: fastapi
Requires-Dist: fastjsonschema
Requires-Dist: ffmpy
Requires-Dist: filelock
Requires-Dist: flatbuffers
Requires-Dist: fonttools
Requires-Dist: fqdn
Requires-Dist: frozenlist
Requires-Dist: fsspec
Requires-Dist: gensim
Requires-Dist: gitdb
Requires-Dist: google-ai-generativelanguage
Requires-Dist: google-api-core
Requires-Dist: google-auth
Requires-Dist: google-generativeai
Requires-Dist: googleapis-common-protos
Requires-Dist: gpustat
Requires-Dist: gradio
Requires-Dist: gradio-client
Requires-Dist: grpcio
Requires-Dist: grpcio-status
Requires-Dist: h11
Requires-Dist: httpcore
Requires-Dist: httptools
Requires-Dist: httpx
Requires-Dist: huggingface-hub
Requires-Dist: humanfriendly
Requires-Dist: id
Requires-Dist: idna
Requires-Dist: imageio
Requires-Dist: importlib-metadata
Requires-Dist: importlib-resources
Requires-Dist: intel-cmplr-lib-rt
Requires-Dist: intel-cmplr-lib-ur
Requires-Dist: intel-cmplr-lic-rt
Requires-Dist: intel-opencl-rt
Requires-Dist: intel-openmp
Requires-Dist: intel-sycl-rt
Requires-Dist: ipykernel
Requires-Dist: ipython
Requires-Dist: ipywidgets
Requires-Dist: isodate
Requires-Dist: isoduration
Requires-Dist: jaraco.classes
Requires-Dist: jaraco.context
Requires-Dist: jaraco.functools
Requires-Dist: jedi
Requires-Dist: jeepney
Requires-Dist: jinja2
Requires-Dist: jiter
Requires-Dist: joblib
Requires-Dist: json5
Requires-Dist: jsonpointer
Requires-Dist: jsonschema
Requires-Dist: jsonschema-specifications
Requires-Dist: jupyter
Requires-Dist: jupyter-client
Requires-Dist: jupyter-console
Requires-Dist: jupyter-core
Requires-Dist: jupyter-events
Requires-Dist: jupyter-lsp
Requires-Dist: jupyter-server
Requires-Dist: jupyter-server-terminals
Requires-Dist: jupyterlab
Requires-Dist: jupyterlab-pygments
Requires-Dist: jupyterlab-server
Requires-Dist: jupyterlab-widgets
Requires-Dist: keyring
Requires-Dist: kiwisolver
Requires-Dist: kubernetes
Requires-Dist: lazy-loader
Requires-Dist: lit
Requires-Dist: llvmlite
Requires-Dist: markdown-it-py
Requires-Dist: matplotlib
Requires-Dist: matplotlib-inline
Requires-Dist: mdurl
Requires-Dist: mistune
Requires-Dist: mkl
Requires-Dist: mkl-fft
Requires-Dist: mkl-service
Requires-Dist: mmh3
Requires-Dist: monotonic
Requires-Dist: more-itertools
Requires-Dist: mpmath
Requires-Dist: msrest
Requires-Dist: multidict
Requires-Dist: multiprocess
Requires-Dist: nbclient
Requires-Dist: nbconvert
Requires-Dist: nbformat
Requires-Dist: nest-asyncio
Requires-Dist: networkx
Requires-Dist: nh3
Requires-Dist: notebook
Requires-Dist: notebook-shim
Requires-Dist: numba
Requires-Dist: numpy
Requires-Dist: nvidia-cublas-cu11
Requires-Dist: nvidia-cuda-cupti-cu11
Requires-Dist: nvidia-cuda-nvrtc-cu11
Requires-Dist: nvidia-cuda-runtime-cu11
Requires-Dist: nvidia-cudnn-cu11
Requires-Dist: nvidia-cufft-cu11
Requires-Dist: nvidia-curand-cu11
Requires-Dist: nvidia-cusolver-cu11
Requires-Dist: nvidia-cusparse-cu11
Requires-Dist: nvidia-ml-py
Requires-Dist: nvidia-nccl-cu11
Requires-Dist: nvidia-nvtx-cu11
Requires-Dist: oauthlib
Requires-Dist: onnxruntime
Requires-Dist: openai
Requires-Dist: opentelemetry-api
Requires-Dist: opentelemetry-exporter-otlp-proto-common
Requires-Dist: opentelemetry-exporter-otlp-proto-grpc
Requires-Dist: opentelemetry-instrumentation
Requires-Dist: opentelemetry-instrumentation-asgi
Requires-Dist: opentelemetry-instrumentation-fastapi
Requires-Dist: opentelemetry-proto
Requires-Dist: opentelemetry-sdk
Requires-Dist: opentelemetry-semantic-conventions
Requires-Dist: opentelemetry-util-http
Requires-Dist: orjson
Requires-Dist: overrides
Requires-Dist: packaging
Requires-Dist: pandas
Requires-Dist: pandocfilters
Requires-Dist: parso
Requires-Dist: pexpect
Requires-Dist: pip
Requires-Dist: platformdirs
Requires-Dist: posthog
Requires-Dist: prometheus-client
Requires-Dist: prompt-toolkit
Requires-Dist: proto-plus
Requires-Dist: protobuf
Requires-Dist: psutil
Requires-Dist: ptyprocess
Requires-Dist: pulsar-client
Requires-Dist: pure-eval
Requires-Dist: pyarrow
Requires-Dist: pyarrow-hotfix
Requires-Dist: pyasn1
Requires-Dist: pyasn1-modules
Requires-Dist: pycparser
Requires-Dist: pydantic
Requires-Dist: pydantic-core
Requires-Dist: pydub
Requires-Dist: pygments
Requires-Dist: pyparsing
Requires-Dist: python-dateutil
Requires-Dist: python-dotenv
Requires-Dist: python-json-logger
Requires-Dist: python-multipart
Requires-Dist: python-utils
Requires-Dist: pytz
Requires-Dist: pyzmq
Requires-Dist: qtconsole
Requires-Dist: readme-renderer
Requires-Dist: referencing
Requires-Dist: regex
Requires-Dist: requests
Requires-Dist: requests-oauthlib
Requires-Dist: requests-toolbelt
Requires-Dist: rfc3339-validator
Requires-Dist: rfc3986
Requires-Dist: rfc3986-validator
Requires-Dist: rich
Requires-Dist: rpds-py
Requires-Dist: rsa
Requires-Dist: ruff
Requires-Dist: safetensors
Requires-Dist: scikit-image
Requires-Dist: scikit-learn
Requires-Dist: scipy
Requires-Dist: seaborn
Requires-Dist: semantic-version
Requires-Dist: sentence-transformers
Requires-Dist: sentencepiece
Requires-Dist: sentry-sdk
Requires-Dist: setproctitle
Requires-Dist: setuptools
Requires-Dist: shellingham
Requires-Dist: shtab
Requires-Dist: six
Requires-Dist: smart-open
Requires-Dist: smmap
Requires-Dist: sniffio
Requires-Dist: soupsieve
Requires-Dist: stack-data
Requires-Dist: starlette
Requires-Dist: sympy
Requires-Dist: tbb
Requires-Dist: tcmlib
Requires-Dist: tenacity
Requires-Dist: tensorboardX
Requires-Dist: terminado
Requires-Dist: texttable
Requires-Dist: threadpoolctl
Requires-Dist: tifffile
Requires-Dist: tinycss2
Requires-Dist: tokenizers
Requires-Dist: tomli
Requires-Dist: tomlkit
Requires-Dist: torch
Requires-Dist: torchaudio
Requires-Dist: torchvision
Requires-Dist: tornado
Requires-Dist: tqdm
Requires-Dist: traitlets
Requires-Dist: transformers
Requires-Dist: triton
Requires-Dist: trl
Requires-Dist: twine
Requires-Dist: typer
Requires-Dist: types-python-dateutil
Requires-Dist: typing-extensions
Requires-Dist: tyro
Requires-Dist: tzdata
Requires-Dist: umf
Requires-Dist: uri-template
Requires-Dist: urllib3
Requires-Dist: utils
Requires-Dist: uvicorn
Requires-Dist: uvloop
Requires-Dist: wandb
Requires-Dist: watchfiles
Requires-Dist: wcwidth
Requires-Dist: webcolors
Requires-Dist: webencodings
Requires-Dist: websocket-client
Requires-Dist: websockets
Requires-Dist: wheel
Requires-Dist: widgetsnbextension
Requires-Dist: wrapt
Requires-Dist: xxhash
Requires-Dist: yarl
Requires-Dist: zipp
Requires-Dist: autocommand
Requires-Dist: inflect
Requires-Dist: jaraco.collections
Requires-Dist: jaraco.text
Requires-Dist: typeguard
